{
  "_meta": {
    "updated_at": "2026-06-18T10:23:56Z",
    "last_session": "2026-06-17",
    "version": 1
  },
  "positions": [
    {
      "id": 16,
      "ticker": "MPAA",
      "scan_date": "2026-06-08",
      "entry_price": 14.25,
      "gap_pct": 32.29,
      "vol_ratio": 16.52,
      "magna_score": 57,
      "strategy_type": "EP",
      "ep_type": "STORY/NEGLECTED",
      "oneil_score": 0,
      "oneil_grade": "",
      "oneil_setup": "",
      "entry_window": "PRIME",
      "stop_price": 12.94,
      "stop_pct": 9.2,
      "prev_close": 10.59,
      "catalyst": "—",
      "thesis": "",
      "sector": "Consumer Cyclical",
      "float_m": 0.0,
      "status": "OPEN",
      "current_price": 14.93,
      "max_price": 15.09,
      "min_price": 13.2,
      "last_updated": "2026-06-17",
      "return_pct": 4.77,
      "hold_days": 10,
      "kb_saved": 0
    },
    {
      "id": 17,
      "ticker": "NUVL",
      "scan_date": "2026-06-09",
      "entry_price": 123.25,
      "gap_pct": 38.8,
      "vol_ratio": 42.18,
      "magna_score": 53,
      "strategy_type": "EP",
      "ep_type": "STORY/NEGLECTED",
      "oneil_score": 0,
      "oneil_grade": "",
      "oneil_setup": "",
      "entry_window": "PRIME",
      "stop_price": 122.8,
      "stop_pct": 0.4,
      "prev_close": 88.49,
      "catalyst": "—",
      "thesis": "",
      "sector": "Healthcare",
      "float_m": 0.0,
      "status": "OPEN",
      "current_price": 123.36,
      "max_price": 123.45,
      "min_price": 123.25,
      "last_updated": "2026-06-17",
      "return_pct": 0.09,
      "hold_days": 9,
      "kb_saved": 0
    },
    {
      "id": 18,
      "ticker": "QURE",
      "scan_date": "2026-06-17",
      "entry_price": 48.16,
      "gap_pct": 61.36,
      "vol_ratio": 32.13,
      "magna_score": 63,
      "strategy_type": "EP",
      "ep_type": "9M_EP",
      "oneil_score": 0,
      "oneil_grade": "",
      "oneil_setup": "",
      "entry_window": "PRIME",
      "stop_price": 42.5,
      "stop_pct": 11.8,
      "prev_close": 26.99,
      "catalyst": "—",
      "thesis": "",
      "sector": "Healthcare",
      "float_m": 0.0,
      "status": "OPEN",
      "current_price": 48.16,
      "max_price": 48.16,
      "min_price": 48.16,
      "last_updated": "2026-06-17",
      "return_pct": 0.0,
      "hold_days": 1,
      "kb_saved": 0
    },
    {
      "id": 19,
      "ticker": "CLPT",
      "scan_date": "2026-06-17",
      "entry_price": 16.81,
      "gap_pct": 36.06,
      "vol_ratio": 28.45,
      "magna_score": 61,
      "strategy_type": "EP",
      "ep_type": "9M_EP",
      "oneil_score": 0,
      "oneil_grade": "",
      "oneil_setup": "",
      "entry_window": "PRIME",
      "stop_price": 16.67,
      "stop_pct": 0.8,
      "prev_close": 13.34,
      "catalyst": "—",
      "thesis": "",
      "sector": "Healthcare",
      "float_m": 0.0,
      "status": "OPEN",
      "current_price": 16.81,
      "max_price": 16.81,
      "min_price": 16.81,
      "last_updated": "2026-06-17",
      "return_pct": 0.0,
      "hold_days": 1,
      "kb_saved": 0
    }
  ]
}